{
  "fetched_from": "goldapi.io",
  "updated_at": "2026-01-08T08:59:17.736Z",
  "rates": {
    "gold": {
      "per_oz": 3797.19,
      "raw": {
        "timestamp": 1767862763,
        "metal": "XAU",
        "currency": "EUR",
        "exchange": "FOREXCOM",
        "symbol": "FOREXCOM:XAUEUR",
        "prev_close_price": 3816.9,
        "open_price": 3816.9,
        "low_price": 3779.96,
        "high_price": 3824.94,
        "open_time": 1767830400,
        "price": 3797.19,
        "ch": -19.71,
        "chp": -0.52,
        "ask": 3797.67,
        "bid": 3796.54,
        "price_gram_24k": 122.0825,
        "price_gram_22k": 111.909,
        "price_gram_21k": 106.8222,
        "price_gram_20k": 101.7354,
        "price_gram_18k": 91.5619,
        "price_gram_16k": 81.3883,
        "price_gram_14k": 71.2148,
        "price_gram_10k": 50.8677
      }
    },
    "silver": {
      "per_oz": 64.86,
      "raw": {
        "timestamp": 1767862765,
        "metal": "XAG",
        "currency": "EUR",
        "exchange": "SAXO",
        "symbol": "SAXO:XAGEUR",
        "prev_close_price": 66.98,
        "open_price": 66.98,
        "low_price": 64.439,
        "high_price": 67.675,
        "open_time": 1767830400,
        "price": 64.86,
        "ch": -2.12,
        "chp": -3.17,
        "ask": 64.883,
        "bid": 64.833,
        "price_gram_24k": 2.0853,
        "price_gram_22k": 1.9115,
        "price_gram_21k": 1.8246,
        "price_gram_20k": 1.7377,
        "price_gram_18k": 1.564,
        "price_gram_16k": 1.3902,
        "price_gram_14k": 1.2164,
        "price_gram_10k": 0.8689
      }
    },
    "platinum": {
      "per_oz": 1889.22,
      "raw": {
        "timestamp": 1767862763,
        "metal": "XPT",
        "currency": "EUR",
        "exchange": "IDC",
        "symbol": "FX_IDC:XPTEUR",
        "prev_close_price": 1955.1,
        "open_price": 1964.9,
        "low_price": 1883.82,
        "high_price": 1987.6,
        "open_time": 1767830400,
        "price": 1889.22,
        "ch": -65.88,
        "chp": -3.37,
        "ask": 1909.22,
        "bid": 1889.22,
        "price_gram_24k": 60.7398,
        "price_gram_22k": 55.6782,
        "price_gram_21k": 53.1474,
        "price_gram_20k": 50.6165,
        "price_gram_18k": 45.5549,
        "price_gram_16k": 40.4932,
        "price_gram_14k": 35.4316,
        "price_gram_10k": 25.3083
      }
    },
    "palladium": {
      "per_oz": 1469.37,
      "raw": {
        "timestamp": 1767862763,
        "metal": "XPD",
        "currency": "EUR",
        "exchange": "IDC",
        "symbol": "FX_IDC:XPDEUR",
        "prev_close_price": 1516.24,
        "open_price": 1516.47,
        "low_price": 1464.03,
        "high_price": 1536.86,
        "open_time": 1767830400,
        "price": 1469.37,
        "ch": -46.87,
        "chp": -3.09,
        "ask": 1477.37,
        "bid": 1469.37,
        "price_gram_24k": 47.2413,
        "price_gram_22k": 43.3046,
        "price_gram_21k": 41.3362,
        "price_gram_20k": 39.3678,
        "price_gram_18k": 35.431,
        "price_gram_16k": 31.4942,
        "price_gram_14k": 27.5574,
        "price_gram_10k": 19.6839
      }
    }
  }
}